icat_plus_client/__init__.py
icat_plus_client/api_client.py
icat_plus_client/api_response.py
icat_plus_client/configuration.py
icat_plus_client/exceptions.py
icat_plus_client/py.typed
icat_plus_client/rest.py
icat_plus_client/api/__init__.py
icat_plus_client/api/actions_api.py
icat_plus_client/api/cache_api.py
icat_plus_client/api/catalogue_api.py
icat_plus_client/api/data_acquisition_api.py
icat_plus_client/api/dmp_api.py
icat_plus_client/api/doi_api.py
icat_plus_client/api/elastic_search_api.py
icat_plus_client/api/ewoks_api.py
icat_plus_client/api/h5_grove_api.py
icat_plus_client/api/ids_api.py
icat_plus_client/api/logbook_api.py
icat_plus_client/api/messages_api.py
icat_plus_client/api/oaipmh_api.py
icat_plus_client/api/panosc_api.py
icat_plus_client/api/resource_api.py
icat_plus_client/api/sample_metadata_api.py
icat_plus_client/api/session_api.py
icat_plus_client/api/tracking_api.py
icat_plus_client/api/user_management_api.py
icat_plus_client/api/users_api.py
icat_plus_client/models/__init__.py
icat_plus_client/models/actions.py
icat_plus_client/models/address.py
icat_plus_client/models/authors_inner.py
icat_plus_client/models/cache_stats.py
icat_plus_client/models/cache_user_storage.py
icat_plus_client/models/catalogue_session_id_instrumentscientist_delete_request.py
icat_plus_client/models/catalogue_session_id_instrumentscientist_put_request.py
icat_plus_client/models/catalogue_session_id_investigation_id_investigation_id_investigationusers_post_request.py
icat_plus_client/models/credentials.py
icat_plus_client/models/dataacquisition_api_key_base64_post_request.py
icat_plus_client/models/dataacquisition_api_key_dataset_restore_post_request.py
icat_plus_client/models/dataacquisition_api_key_mint_post200_response.py
icat_plus_client/models/dataacquisition_api_key_mint_post_request.py
icat_plus_client/models/datacollection.py
icat_plus_client/models/datacollection_data_collection_datasets_inner.py
icat_plus_client-4.54.1.dist-info/METADATA
icat_plus_client-4.54.1.dist-info/WHEEL
icat_plus_client-4.54.1.dist-info/top_level.txt
icat_plus_client-4.54.1.dist-info/RECORD
