Metadata-Version: 2.4
Name: icat-plus-client
Version: 4.54.1
Summary: ICAT+ API
Home-page: 
Author:  Alejandro De Maria Antolinos
Author-email: demariaa@esrf.fr
License: MIT
Keywords: OpenAPI,OpenAPI-Generator,ICAT+ API
Requires-Dist: urllib3<2.1.0,>=1.25.3
Requires-Dist: python-dateutil
Requires-Dist: pydantic>=2
Requires-Dist: typing-extensions>=4.7.1
Dynamic: author
Dynamic: author-email
Dynamic: description
Dynamic: description-content-type
Dynamic: keywords
Dynamic: license
Dynamic: requires-dist
Dynamic: summary
